{"dependencies":[{"name":"./App.js","loc":{"line":1,"column":20}},{"name":"jquery","loc":{"line":2,"column":18}}],"generated":{"js":"const App = require(\"./App.js\")\nconst $ = require(\"jquery\")\n\nclass Top250 extends App {\n  constructor(wrap) {\n    super(wrap);\n    this.index = 0;\n    this.count = 10;\n    this.loading = false;\n    this.isFinished = false\n  }\n\n  init() {\n    this.getData()\n    this.bindEvents()\n  };\n\n  getData() {\n    if (this.isFinished) return\n    if (this.loading) return;\n    this.loading = true\n    this.wrap.find(`.loading`).addClass('a')\n    $.ajax({\n      type: \"get\",\n      url: \"https://api.douban.com/v2/movie/top250\",\n      data: {\n        start: this.index,\n        count: this.count\n      },\n      dataType: \"jsonp\"\n    }).done((json) => {\n      this.index += 10\n      json.subjects.forEach((ele, index) => {\n        this.wrap.find(\".container\").append(super.createNode(ele))\n      })\n      if (this.strat > json.total) {\n        this.isFinished = true\n      }\n    }).fail(() => {\n      console.log(\"error\");\n    }).always(() => {\n      this.loading = false\n      this.wrap.find(`.loading`).removeClass(\"a\")\n    })\n  }\n\n  isEnd($viewport, $content) {\n    return $viewport.height() + $viewport.scrollTop() + 10 >= $content.height()\n  };\n  bindEvents() {\n    let _this = this\n    this.wrap.scroll(function(event) {\n      if (_this.isEnd($(this), $(this).find(`.container`))) {\n        _this.getData()\n      }\n    });\n\n\n  };\n}\n\n\n\nmodule.exports = Top250","map":{"mappings":[{"source":"js/Top250.js","original":{"line":1,"column":0},"generated":{"line":1,"column":0}},{"source":"js/Top250.js","original":{"line":2,"column":0},"generated":{"line":2,"column":0}},{"source":"js/Top250.js","original":{"line":3,"column":0},"generated":{"line":3,"column":0}},{"source":"js/Top250.js","original":{"line":4,"column":0},"generated":{"line":4,"column":0}},{"source":"js/Top250.js","original":{"line":5,"column":0},"generated":{"line":5,"column":0}},{"source":"js/Top250.js","original":{"line":6,"column":0},"generated":{"line":6,"column":0}},{"source":"js/Top250.js","original":{"line":7,"column":0},"generated":{"line":7,"column":0}},{"source":"js/Top250.js","original":{"line":8,"column":0},"generated":{"line":8,"column":0}},{"source":"js/Top250.js","original":{"line":9,"column":0},"generated":{"line":9,"column":0}},{"source":"js/Top250.js","original":{"line":10,"column":0},"generated":{"line":10,"column":0}},{"source":"js/Top250.js","original":{"line":11,"column":0},"generated":{"line":11,"column":0}},{"source":"js/Top250.js","original":{"line":12,"column":0},"generated":{"line":12,"column":0}},{"source":"js/Top250.js","original":{"line":13,"column":0},"generated":{"line":13,"column":0}},{"source":"js/Top250.js","original":{"line":14,"column":0},"generated":{"line":14,"column":0}},{"source":"js/Top250.js","original":{"line":15,"column":0},"generated":{"line":15,"column":0}},{"source":"js/Top250.js","original":{"line":16,"column":0},"generated":{"line":16,"column":0}},{"source":"js/Top250.js","original":{"line":17,"column":0},"generated":{"line":17,"column":0}},{"source":"js/Top250.js","original":{"line":18,"column":0},"generated":{"line":18,"column":0}},{"source":"js/Top250.js","original":{"line":19,"column":0},"generated":{"line":19,"column":0}},{"source":"js/Top250.js","original":{"line":20,"column":0},"generated":{"line":20,"column":0}},{"source":"js/Top250.js","original":{"line":21,"column":0},"generated":{"line":21,"column":0}},{"source":"js/Top250.js","original":{"line":22,"column":0},"generated":{"line":22,"column":0}},{"source":"js/Top250.js","original":{"line":23,"column":0},"generated":{"line":23,"column":0}},{"source":"js/Top250.js","original":{"line":24,"column":0},"generated":{"line":24,"column":0}},{"source":"js/Top250.js","original":{"line":25,"column":0},"generated":{"line":25,"column":0}},{"source":"js/Top250.js","original":{"line":26,"column":0},"generated":{"line":26,"column":0}},{"source":"js/Top250.js","original":{"line":27,"column":0},"generated":{"line":27,"column":0}},{"source":"js/Top250.js","original":{"line":28,"column":0},"generated":{"line":28,"column":0}},{"source":"js/Top250.js","original":{"line":29,"column":0},"generated":{"line":29,"column":0}},{"source":"js/Top250.js","original":{"line":30,"column":0},"generated":{"line":30,"column":0}},{"source":"js/Top250.js","original":{"line":31,"column":0},"generated":{"line":31,"column":0}},{"source":"js/Top250.js","original":{"line":32,"column":0},"generated":{"line":32,"column":0}},{"source":"js/Top250.js","original":{"line":33,"column":0},"generated":{"line":33,"column":0}},{"source":"js/Top250.js","original":{"line":34,"column":0},"generated":{"line":34,"column":0}},{"source":"js/Top250.js","original":{"line":35,"column":0},"generated":{"line":35,"column":0}},{"source":"js/Top250.js","original":{"line":36,"column":0},"generated":{"line":36,"column":0}},{"source":"js/Top250.js","original":{"line":37,"column":0},"generated":{"line":37,"column":0}},{"source":"js/Top250.js","original":{"line":38,"column":0},"generated":{"line":38,"column":0}},{"source":"js/Top250.js","original":{"line":39,"column":0},"generated":{"line":39,"column":0}},{"source":"js/Top250.js","original":{"line":40,"column":0},"generated":{"line":40,"column":0}},{"source":"js/Top250.js","original":{"line":41,"column":0},"generated":{"line":41,"column":0}},{"source":"js/Top250.js","original":{"line":42,"column":0},"generated":{"line":42,"column":0}},{"source":"js/Top250.js","original":{"line":43,"column":0},"generated":{"line":43,"column":0}},{"source":"js/Top250.js","original":{"line":44,"column":0},"generated":{"line":44,"column":0}},{"source":"js/Top250.js","original":{"line":45,"column":0},"generated":{"line":45,"column":0}},{"source":"js/Top250.js","original":{"line":46,"column":0},"generated":{"line":46,"column":0}},{"source":"js/Top250.js","original":{"line":47,"column":0},"generated":{"line":47,"column":0}},{"source":"js/Top250.js","original":{"line":48,"column":0},"generated":{"line":48,"column":0}},{"source":"js/Top250.js","original":{"line":49,"column":0},"generated":{"line":49,"column":0}},{"source":"js/Top250.js","original":{"line":50,"column":0},"generated":{"line":50,"column":0}},{"source":"js/Top250.js","original":{"line":51,"column":0},"generated":{"line":51,"column":0}},{"source":"js/Top250.js","original":{"line":52,"column":0},"generated":{"line":52,"column":0}},{"source":"js/Top250.js","original":{"line":53,"column":0},"generated":{"line":53,"column":0}},{"source":"js/Top250.js","original":{"line":54,"column":0},"generated":{"line":54,"column":0}},{"source":"js/Top250.js","original":{"line":55,"column":0},"generated":{"line":55,"column":0}},{"source":"js/Top250.js","original":{"line":56,"column":0},"generated":{"line":56,"column":0}},{"source":"js/Top250.js","original":{"line":57,"column":0},"generated":{"line":57,"column":0}},{"source":"js/Top250.js","original":{"line":58,"column":0},"generated":{"line":58,"column":0}},{"source":"js/Top250.js","original":{"line":59,"column":0},"generated":{"line":59,"column":0}},{"source":"js/Top250.js","original":{"line":60,"column":0},"generated":{"line":60,"column":0}},{"source":"js/Top250.js","original":{"line":61,"column":0},"generated":{"line":61,"column":0}},{"source":"js/Top250.js","original":{"line":62,"column":0},"generated":{"line":62,"column":0}},{"source":"js/Top250.js","original":{"line":63,"column":0},"generated":{"line":63,"column":0}},{"source":"js/Top250.js","original":{"line":64,"column":0},"generated":{"line":64,"column":0}}],"sources":{"js/Top250.js":"const App = require(\"./App.js\")\nconst $ = require(\"jquery\")\n\nclass Top250 extends App {\n  constructor(wrap) {\n    super(wrap);\n    this.index = 0;\n    this.count = 10;\n    this.loading = false;\n    this.isFinished = false\n  }\n\n  init() {\n    this.getData()\n    this.bindEvents()\n  };\n\n  getData() {\n    if (this.isFinished) return\n    if (this.loading) return;\n    this.loading = true\n    this.wrap.find(`.loading`).addClass('a')\n    $.ajax({\n      type: \"get\",\n      url: \"https://api.douban.com/v2/movie/top250\",\n      data: {\n        start: this.index,\n        count: this.count\n      },\n      dataType: \"jsonp\"\n    }).done((json) => {\n      this.index += 10\n      json.subjects.forEach((ele, index) => {\n        this.wrap.find(\".container\").append(super.createNode(ele))\n      })\n      if (this.strat > json.total) {\n        this.isFinished = true\n      }\n    }).fail(() => {\n      console.log(\"error\");\n    }).always(() => {\n      this.loading = false\n      this.wrap.find(`.loading`).removeClass(\"a\")\n    })\n  }\n\n  isEnd($viewport, $content) {\n    return $viewport.height() + $viewport.scrollTop() + 10 >= $content.height()\n  };\n  bindEvents() {\n    let _this = this\n    this.wrap.scroll(function(event) {\n      if (_this.isEnd($(this), $(this).find(`.container`))) {\n        _this.getData()\n      }\n    });\n\n\n  };\n}\n\n\n\nmodule.exports = Top250"},"lineCount":64}},"hash":"2fe3b65933961189177a92bf171ee454","cacheData":{"env":{}}}